Metadata-Version: 2.1
Name: PyPack01
Version: 0.0.1
Summary: Pacote python para exibir número de 1 a 9
Home-page: https://www.imfdb.org/wiki/Counter-Strike:_Global_Offensive#Colt_Model_723
Author: Fellipe Torres Santos
Author-email: bravohawkr3st4g5658@gmail.com
License: MIT License
Keywords: Pacote
Platform: UNKNOWN
License-File: LICENSE
